color2vec/__init__.py
color2vec/src/RGB_to_vec.py
color2vec/src/__init__.py
color2vec/src/annoy_similarity.py
color2vec/src/color2vec.py
color2vec/src/lab.py
color2vec/src/string_to_RGB.py
color2vec/src/data/advanced.csv
color2vec/src/data/basic.csv
color2vec/src/data/colors.csv
color2vec/src/data/colors_1.csv
color2vec/src/data/pantone.csv
color2vec/src/data/ultra_basic.csv
color2vec/src/model/__init__.py
color2vec/src/model/color_siames_model.h5
color2vec/src/model/string_to_rgb_model.h5
color2vec/src/model/tokenizer.json
color2vec/src/model/tokenizer.pickle
color2vec-1.0.3.dist-info/METADATA
color2vec-1.0.3.dist-info/WHEEL
color2vec-1.0.3.dist-info/top_level.txt
color2vec-1.0.3.dist-info/RECORD
