Metadata-Version: 2.1
Name: color2vec
Version: 1.0.3
Summary: Greendeck color to vector package.
Home-page: UNKNOWN
Author: chandan mishra
Author-email: chandan.mishra@greendeck.co
License: UNKNOWN
Platform: UNKNOWN
Classifier: Programming Language :: Python :: 3
Classifier: License :: OSI Approved :: MIT License
Classifier: Operating System :: OS Independent
Requires-Dist: tensorflow (<2.0.0,>=1.8.0)
Requires-Dist: tqdm
Requires-Dist: numpy
Requires-Dist: pandas
Requires-Dist: annoy
Requires-Dist: keras (==2.1.5)
Requires-Dist: scipy
